<?xml version="1.0" encoding="ISO-8859-1"?>
<!-- XML generated by UTFXML Version 2.2 built 19-Aug-2010 -->
<UTFXML filename="prop_sinclair_mask.3db" path="CHARACTERS\PROPS">
   <UTF_ROOT>
      <VMeshLibrary>
         <data.characters.props.prop_sinclair_mask.lod0-112.vms include="prop_sinclair_mask_3db\lod0-112.vms.xml"/>
      </VMeshLibrary>
      <Exporter_Version name="Exporter Version" type="text">Mar  4 2002 16:05:38</Exporter_Version>
      <VMeshPart>
         <VMeshRef type="VMeshRef">
            <!-- header size  --> 60,
            <!-- vmesh lib    --> data.characters.props.prop_sinclair_mask.lod0-112.vms,
            <!-- start vert   --> 0,
            <!-- num verts    --> 564,
            <!-- start index  --> 0,
            <!-- num indices  --> 1548,
            <!-- start mesh   --> 0,
            <!-- num meshes   --> 2,
            <!-- bounding box -->  0.075414807,   0.067495659,   0.079682708,
                                  -0.072240405,  -0.056904323,  -0.043938115,
            <!-- center       -->  0.0031027468,  0.0096402289,  0.016572336,
            <!-- radius       --> 0.080016956
         </VMeshRef>
      </VMeshPart>
      <Hardpoints>
         <Fixed>
            <hp_head_Mask>
               <Position type="Vector">0.0020674723, 0.076432876, 0.073594928</Position>
               <Orientation type="Matrix">
                    1.0000000000, -844.17513e-09,  325.01717e-09,
                   844.17474e-09,   1.0000000000,  1.1382995e-06,
                  -325.01814e-09, -1.1382992e-06,   1.0000000000
               </Orientation>
            </hp_head_Mask>
            <HpRightConnect>
               <Position type="Vector">-0.0034901691, -0.074203365, -0.079624772</Position>
               <Orientation type="Matrix">
                    0.8919359400,  -0.4338032300,   0.1275346100,
                   -0.4487958800,  -0.8150000000,   0.3665476100,
                   -0.0550688170,  -0.3841739900,  -0.9216169100
               </Orientation>
            </HpRightConnect>
         </Fixed>
      </Hardpoints>
      <Material_library name="Material library">
         <Material_count name="Material count" type="int">2</Material_count>
         <Sinclair_Mask name="Sinclair Mask">
            <Type type="text">DcDt</Type>
            <Dt_name type="text">Sinclair mask test.tga</Dt_name>
            <Dt_flags type="int">0x40</Dt_flags>
         </Sinclair_Mask>
         <goggles>
            <Type type="text">DcDt</Type>
            <Dt_name type="text">Sinclair mask goggles.tga</Dt_name>
            <Dt_flags type="int">0x40</Dt_flags>
         </goggles>
      </Material_library>
      <Texture_library name="Texture library">
         <Sinclair_mask_goggles.tga name="Sinclair mask goggles.tga">
            <MIPS type="file" filename="prop_sinclair_mask_3db\Sinclair mask goggles.dds"/>
         </Sinclair_mask_goggles.tga>
         <Sinclair_mask_test.tga name="Sinclair mask test.tga">
            <MIPS type="file" filename="prop_sinclair_mask_3db\Sinclair mask test.dds"/>
         </Sinclair_mask_test.tga>
      </Texture_library>
   </UTF_ROOT>
</UTFXML>
