<?xml version="1.0" encoding="ISO-8859-1"?>
<!-- XML generated by UTFXML Version 2.2 built 19-Aug-2010 -->
<UTFXML filename="cwire_contraband_1.3db" path="EQUIPMENT\MODELS\COMMODITIES\NN_ICONS">
   <UTF_ROOT>
      <VMeshLibrary>
         <data.equipment.models.commodities.nn_icons.cwire_contraband_1.lod0-112.vms include="cwire_contraband_1_3db\lod0-112.vms.xml"/>
      </VMeshLibrary>
      <Exporter_Version name="Exporter Version" type="text">Aug 30 2001 21:08:30</Exporter_Version>
      <VMeshPart>
         <VMeshRef type="VMeshRef">
            <!-- header size  --> 60,
            <!-- vmesh lib    --> data.equipment.models.commodities.nn_icons.cwire_contraband_1.lod0-112.vms,
            <!-- start vert   --> 0,
            <!-- num verts    --> 228,
            <!-- start index  --> 0,
            <!-- num indices  --> 372,
            <!-- start mesh   --> 0,
            <!-- num meshes   --> 2,
            <!-- bounding box -->  0.011194279,   0.015847206,    0.0077181072,
                                  -0.01526364,   -0.016381297,   -0.0077188197,
            <!-- center       --> -0.0023810184, -0.0011197345, 590.81579e-6,
            <!-- radius       --> 0.018675042
         </VMeshRef>
      </VMeshPart>
      <VMeshWire include="cwire_contraband_1_3db\cwire_contraband_1.vwd.xml"/>
      <Hardpoints>
         <Fixed>
            <HpItem>
               <Position type="Vector">-24.289044e-9, 2.0681991e-6, -2.7406265e-6</Position>
               <Orientation type="Matrix">
                   -1.0000000000, -87.422762e-09, -150.99583e-09,
                  -87.422762e-09,   1.0000000000, -15.616350e-15,
                   150.99583e-09, -2.4158773e-15,  -1.0000000000
               </Orientation>
            </HpItem>
         </Fixed>
      </Hardpoints>
      <Material_library name="Material library">
         <Material_count name="Material count" type="int">2</Material_count>
         <weapon_generic.tga>
            <Type type="text">DcDtEc</Type>
            <Dt_name type="text">weapon_generic.tga</Dt_name>
            <Dt_flags type="int">0x40</Dt_flags>
            <Ec type="RGB">1, 1, 1</Ec>
         </weapon_generic.tga>
         <contrabandtexture.tga>
            <Type type="text">DcDtTwo</Type>
            <Dt_name type="text">contrabandtexture.tga</Dt_name>
            <Dt_flags type="int">0x40</Dt_flags>
         </contrabandtexture.tga>
      </Material_library>
      <Texture_library name="Texture library">
         <contrabandtexture.tga>
            <MIP0 type="file" filename="cwire_contraband_1_3db\contrabandtexture_mip0.tga"/>
         </contrabandtexture.tga>
         <weapon_generic.tga>
            <MIP0 type="file" filename="cwire_contraband_1_3db\weapon_generic_mip0.tga"/>
         </weapon_generic.tga>
      </Texture_library>
   </UTF_ROOT>
</UTFXML>
